{
  "api_version": "2026-07-13.1",
  "source": "master-gas:eat",
  "endpoint": "canonicalMasterEndpoint?sheet=eat&lang=ja&status=active",
  "count": 63,
  "items": [
    {
      "id": "baba-münsterstrasse",
      "slug": "baba-münsterstrasse",
      "status": "active",
      "name": "BaBa Sushi Restaurant",
      "title": "BaBa Sushi Restaurant",
      "name_ja": "",
      "name_en": "",
      "category": "🌸和食",
      "category1": "🌸和食",
      "detail_category": "🍣寿司",
      "category2": "🍣寿司",
      "city": "Düsseldorf",
      "region": "Düsseldorf",
      "area": "",
      "address": "Münsterstraße 22, 40477, Düsseldorf",
      "street": "Münsterstraße 22",
      "postcode": "40477",
      "country_code": "DE",
      "short_description": "",
      "description": "",
      "detail_comment": "",
      "description_en": "",
      "tags": "",
      "price": "€20–30",
      "rating": 0,
      "reviews_count": 1848,
      "official_url": "https://www.badory.com/",
      "website": "https://www.badory.com/",
      "map_url": "https://www.google.com/maps/search/?api=1&query=BaBa%20Sushi%20Restaurant&query_place_id=ChIJczIrPU7JuEcR7ws7YQHB5pQ",
      "source_url": "",
      "phone": "",
      "opening_hours": "",
      "language_support": "",
      "latitude": null,
      "longitude": null,
      "last_reviewed_at": "2026-03-27T23:00:00.000Z",
      "updated_at": "2026-03-27T23:00:00.000Z"
    },
    {
      "id": "bymisaki-ackerstrasse",
      "slug": "bymisaki-ackerstrasse",
      "status": "active",
      "name": "byMisaki | Your Japanese Sushi Bar",
      "title": "byMisaki | Your Japanese Sushi Bar",
      "name_ja": "",
      "name_en": "",
      "category": "🌸和食",
      "category1": "🌸和食",
      "detail_category": "🍣寿司",
      "category2": "🍣寿司",
      "city": "Düsseldorf",
      "region": "Düsseldorf",
      "area": "",
      "address": "Ackerstraße 20, 40233, Düsseldorf",
      "street": "Ackerstraße 20",
      "postcode": "40233",
      "country_code": "DE",
      "short_description": "",
      "description": "",
      "detail_comment": "",
      "description_en": "",
      "tags": "",
      "price": "€10–20",
      "rating": 4,
      "reviews_count": 6,
      "official_url": "http://bymisaki.de/?utm_source=google_business_profile&utm_medium=button&utm_tracking_link_id=fbe4bde7-f698-45e7-956f-55425ce2604d",
      "website": "http://bymisaki.de/?utm_source=google_business_profile&utm_medium=button&utm_tracking_link_id=fbe4bde7-f698-45e7-956f-55425ce2604d",
      "map_url": "https://www.google.com/maps/search/?api=1&query=byMisaki%20%7C%20Your%20Japanese%20Sushi%20Bar&query_place_id=ChIJraszmi7LuEcRBZgO8ri1jFk",
      "source_url": "",
      "phone": "",
      "opening_hours": "",
      "language_support": "",
      "latitude": null,
      "longitude": null,
      "last_reviewed_at": "2026-03-27T23:00:00.000Z",
      "updated_at": "2026-03-27T23:00:00.000Z"
    },
    {
      "id": "ChIJIXGSFwq2uEcRRVmeJ7ctAqs",
      "slug": "daidokoro-hansaallee",
      "status": "active",
      "name": "Daidokoro Umaimon",
      "title": "Daidokoro Umaimon",
      "name_ja": "",
      "name_en": "",
      "category": "🌸和食",
      "category1": "🌸和食",
      "detail_category": "🍜ラーメン",
      "category2": "🍜ラーメン",
      "city": "Düsseldorf",
      "region": "Düsseldorf",
      "area": "",
      "address": "Hansaallee 244, 40547, Düsseldorf",
      "street": "Hansaallee 244",
      "postcode": "40547",
      "country_code": "DE",
      "short_description": "",
      "description": "",
      "detail_comment": "",
      "description_en": "",
      "tags": "",
      "price": "€20–30",
      "rating": 0,
      "reviews_count": 1410,
      "official_url": "https://www.brickny.com/deutsch/unsere-restaurants/daidokoro-umaimon-de/",
      "website": "https://www.brickny.com/deutsch/unsere-restaurants/daidokoro-umaimon-de/",
      "map_url": "https://www.google.com/maps/search/?api=1&query=Daidokoro%20Umaimon&query_place_id=ChIJIXGSFwq2uEcRRVmeJ7ctAqs",
      "source_url": "",
      "phone": "",
      "opening_hours": "",
      "language_support": "",
      "latitude": 51.2387885,
      "longitude": 6.7328535,
      "last_reviewed_at": "2026-03-27T23:00:00.000Z",
      "updated_at": "2026-03-27T23:00:00.000Z"
    },
    {
      "id": "ChIJ3U0ISwDJuEcRD4rNhRR6Rp4",
      "slug": "daruma-sommersstrasse",
      "status": "active",
      "name": "Daruma Fusion - Sushi & Asian Restaurant Düsseldorf",
      "title": "Daruma Fusion - Sushi & Asian Restaurant Düsseldorf",
      "name_ja": "",
      "name_en": "",
      "category": "🌸和食",
      "category1": "🌸和食",
      "detail_category": "🍣寿司",
      "category2": "🍣寿司",
      "city": "Düsseldorf",
      "region": "Düsseldorf",
      "area": "",
      "address": "Sommersstraße 19, 40476, Düsseldorf",
      "street": "Sommersstraße 19",
      "postcode": "40476",
      "country_code": "DE",
      "short_description": "",
      "description": "",
      "detail_comment": "",
      "description_en": "",
      "tags": "",
      "price": "€20–30",
      "rating": 0,
      "reviews_count": 255,
      "official_url": "https://daruma-fusion.com/",
      "website": "https://daruma-fusion.com/",
      "map_url": "https://www.google.com/maps/search/?api=1&query=Daruma%20Fusion%20-%20Sushi%20%26%20Asian%20Restaurant%20D%C3%BCsseldorf&query_place_id=ChIJ3U0ISwDJuEcRD4rNhRR6Rp4",
      "source_url": "",
      "phone": "",
      "opening_hours": "",
      "language_support": "",
      "latitude": 51.2452503,
      "longitude": 6.7902711,
      "last_reviewed_at": "2026-03-27T23:00:00.000Z",
      "updated_at": "2026-03-27T23:00:00.000Z"
    },
    {
      "id": "eat-am",
      "slug": "eat-am",
      "status": "active",
      "name": "EAT HAPPY",
      "title": "EAT HAPPY",
      "name_ja": "",
      "name_en": "",
      "category": "🌸和食",
      "category1": "🌸和食",
      "detail_category": "🍣寿司",
      "category2": "🍣寿司",
      "city": "Düsseldorf",
      "region": "Düsseldorf",
      "area": "",
      "address": "Am Wehrhahn 43, 40211, Düsseldorf",
      "street": "Am Wehrhahn 43",
      "postcode": "40211",
      "country_code": "DE",
      "short_description": "",
      "description": "",
      "detail_comment": "",
      "description_en": "",
      "tags": "",
      "price": "",
      "rating": 4,
      "reviews_count": 1,
      "official_url": "https://www.eathappy.de/standorte/?q=40211",
      "website": "https://www.eathappy.de/standorte/?q=40211",
      "map_url": "https://www.google.com/maps/search/?api=1&query=EAT%20HAPPY&query_place_id=ChIJQe1C5ZPLuEcR6JZcv9zs080",
      "source_url": "",
      "phone": "",
      "opening_hours": "",
      "language_support": "",
      "latitude": null,
      "longitude": null,
      "last_reviewed_at": "2026-03-27T23:00:00.000Z",
      "updated_at": "2026-03-27T23:00:00.000Z"
    },
    {
      "id": "eat-bruchstrasse",
      "slug": "eat-bruchstrasse",
      "status": "active",
      "name": "EAT HAPPY",
      "title": "EAT HAPPY",
      "name_ja": "",
      "name_en": "",
      "category": "🌸和食",
      "category1": "🌸和食",
      "detail_category": "🍣寿司",
      "category2": "🍣寿司",
      "city": "Düsseldorf",
      "region": "Düsseldorf",
      "area": "",
      "address": "Bruchstraße 89-91, 40235, Düsseldorf",
      "street": "Bruchstraße 89-91",
      "postcode": "40235",
      "country_code": "DE",
      "short_description": "",
      "description": "",
      "detail_comment": "",
      "description_en": "",
      "tags": "",
      "price": "",
      "rating": 0,
      "reviews_count": 2,
      "official_url": "https://www.eathappy.de/standorte/?q=40235",
      "website": "https://www.eathappy.de/standorte/?q=40235",
      "map_url": "https://www.google.com/maps/search/?api=1&query=EAT%20HAPPY&query_place_id=ChIJI8_QvUDLuEcRFejnB5GyqjU",
      "source_url": "",
      "phone": "",
      "opening_hours": "",
      "language_support": "",
      "latitude": null,
      "longitude": null,
      "last_reviewed_at": "2026-03-27T23:00:00.000Z",
      "updated_at": "2026-03-27T23:00:00.000Z"
    },
    {
      "id": "eat-kaiserswerther",
      "slug": "eat-kaiserswerther",
      "status": "active",
      "name": "EAT HAPPY",
      "title": "EAT HAPPY",
      "name_ja": "",
      "name_en": "",
      "category": "🌸和食",
      "category1": "🌸和食",
      "detail_category": "🍣寿司",
      "category2": "🍣寿司",
      "city": "Düsseldorf",
      "region": "Düsseldorf",
      "area": "",
      "address": "Kaiserswerther Str. 270, 40474, Düsseldorf",
      "street": "Kaiserswerther Str. 270",
      "postcode": "40474",
      "country_code": "DE",
      "short_description": "",
      "description": "",
      "detail_comment": "",
      "description_en": "",
      "tags": "",
      "price": "",
      "rating": 5,
      "reviews_count": 1,
      "official_url": "https://www.eathappy.de/standorte/?q=40474",
      "website": "https://www.eathappy.de/standorte/?q=40474",
      "map_url": "https://www.google.com/maps/search/?api=1&query=EAT%20HAPPY&query_place_id=ChIJG1MbOfDJuEcRf9V3VluWyTo",
      "source_url": "",
      "phone": "",
      "opening_hours": "",
      "language_support": "",
      "latitude": null,
      "longitude": null,
      "last_reviewed_at": "2026-03-27T23:00:00.000Z",
      "updated_at": "2026-03-27T23:00:00.000Z"
    },
    {
      "id": "eat-reisholzer",
      "slug": "eat-reisholzer",
      "status": "active",
      "name": "EAT HAPPY",
      "title": "EAT HAPPY",
      "name_ja": "",
      "name_en": "",
      "category": "🌸和食",
      "category1": "🌸和食",
      "detail_category": "🍣寿司",
      "category2": "🍣寿司",
      "city": "Düsseldorf",
      "region": "Düsseldorf",
      "area": "",
      "address": "Reisholzer Str. 11, 40231, Düsseldorf",
      "street": "Reisholzer Str. 11",
      "postcode": "40231",
      "country_code": "DE",
      "short_description": "",
      "description": "",
      "detail_comment": "",
      "description_en": "",
      "tags": "",
      "price": "",
      "rating": 0,
      "reviews_count": 22,
      "official_url": "https://www.eathappy.de/standorte/?q=40231",
      "website": "https://www.eathappy.de/standorte/?q=40231",
      "map_url": "https://www.google.com/maps/search/?api=1&query=EAT%20HAPPY&query_place_id=ChIJGxHtot_LuEcRu6RzVG93mqs",
      "source_url": "",
      "phone": "",
      "opening_hours": "",
      "language_support": "",
      "latitude": null,
      "longitude": null,
      "last_reviewed_at": "2026-03-27T23:00:00.000Z",
      "updated_at": "2026-03-27T23:00:00.000Z"
    },
    {
      "id": "ChIJ2RNXRCXJuEcRdmuA2SB-1NE",
      "slug": "eat-flughafenstrasse",
      "status": "active",
      "name": "eat TOKYO",
      "title": "eat TOKYO",
      "name_ja": "",
      "name_en": "",
      "category": "🌸和食",
      "category1": "🌸和食",
      "detail_category": "🍣寿司",
      "category2": "🍣寿司",
      "city": "Düsseldorf",
      "region": "Düsseldorf",
      "area": "",
      "address": "Flughafenstraße 120, 40474, Düsseldorf",
      "street": "Flughafenstraße 120",
      "postcode": "40474",
      "country_code": "DE",
      "short_description": "",
      "description": "",
      "detail_comment": "",
      "description_en": "",
      "tags": "",
      "price": "€20–30",
      "rating": 0,
      "reviews_count": 51,
      "official_url": "https://eat-tokyo.com/",
      "website": "https://eat-tokyo.com/",
      "map_url": "https://www.google.com/maps/search/?api=1&query=eat%20TOKYO&query_place_id=ChIJ2RNXRCXJuEcRdmuA2SB-1NE",
      "source_url": "",
      "phone": "",
      "opening_hours": "",
      "language_support": "",
      "latitude": 51.2796587,
      "longitude": 6.7654872,
      "last_reviewed_at": "2026-03-27T23:00:00.000Z",
      "updated_at": "2026-03-27T23:00:00.000Z"
    },
    {
      "id": "ChIJ22ry9z_LuEcRoJXDUfGzZzs",
      "slug": "eattokyo-immermannstrasse",
      "status": "active",
      "name": "eatTOKYO immermann",
      "title": "eatTOKYO immermann",
      "name_ja": "",
      "name_en": "",
      "category": "🌸和食",
      "category1": "🌸和食",
      "detail_category": "🍣寿司",
      "category2": "🍣寿司",
      "city": "Düsseldorf",
      "region": "Düsseldorf",
      "area": "",
      "address": "Immermannstraße 40, 40210, Düsseldorf",
      "street": "Immermannstraße 40",
      "postcode": "40210",
      "country_code": "DE",
      "short_description": "",
      "description": "",
      "detail_comment": "",
      "description_en": "",
      "tags": "",
      "price": "€10–20",
      "rating": 0,
      "reviews_count": 2027,
      "official_url": "https://www.eat-tokyo.com/",
      "website": "https://www.eat-tokyo.com/",
      "map_url": "https://www.google.com/maps/search/?api=1&query=eatTOKYO%20immermann&query_place_id=ChIJ22ry9z_LuEcRoJXDUfGzZzs",
      "source_url": "",
      "phone": "",
      "opening_hours": "",
      "language_support": "",
      "latitude": 51.2232794,
      "longitude": 6.7900175,
      "last_reviewed_at": "2026-03-27T23:00:00.000Z",
      "updated_at": "2026-03-27T23:00:00.000Z"
    },
    {
      "id": "ChIJc_JhxZvJuEcR51DuaLQAVa8",
      "slug": "funky-münsterstrasse",
      "status": "active",
      "name": "Funky Ramen",
      "title": "Funky Ramen",
      "name_ja": "",
      "name_en": "",
      "category": "🌸和食",
      "category1": "🌸和食",
      "detail_category": "🍣寿司",
      "category2": "🍣寿司",
      "city": "Düsseldorf",
      "region": "Düsseldorf",
      "area": "",
      "address": "Münsterstraße 33, 40477, Düsseldorf",
      "street": "Münsterstraße 33",
      "postcode": "40477",
      "country_code": "DE",
      "short_description": "",
      "description": "",
      "detail_comment": "",
      "description_en": "",
      "tags": "",
      "price": "€20–30",
      "rating": 0,
      "reviews_count": 867,
      "official_url": "https://funky-ramen.de/",
      "website": "https://funky-ramen.de/",
      "map_url": "https://www.google.com/maps/search/?api=1&query=Funky%20Ramen&query_place_id=ChIJc_JhxZvJuEcR51DuaLQAVa8",
      "source_url": "",
      "phone": "",
      "opening_hours": "",
      "language_support": "",
      "latitude": 51.2421472,
      "longitude": 6.7842103,
      "last_reviewed_at": "2026-03-27T23:00:00.000Z",
      "updated_at": "2026-03-27T23:00:00.000Z"
    },
    {
      "id": "genki-hansaallee",
      "slug": "genki-hansaallee",
      "status": "active",
      "name": "Genki Sushi Restaurant",
      "title": "Genki Sushi Restaurant",
      "name_ja": "",
      "name_en": "",
      "category": "🌸和食",
      "category1": "🌸和食",
      "detail_category": "🍣寿司",
      "category2": "🍣寿司",
      "city": "Düsseldorf",
      "region": "Düsseldorf",
      "area": "",
      "address": "Hansaallee 163B, 40549, Düsseldorf",
      "street": "Hansaallee 163B",
      "postcode": "40549",
      "country_code": "DE",
      "short_description": "",
      "description": "",
      "detail_comment": "",
      "description_en": "",
      "tags": "",
      "price": "",
      "rating": 4,
      "reviews_count": 55,
      "official_url": "https://www.genki-bowlosushiogrill-duesseldorf.de/",
      "website": "https://www.genki-bowlosushiogrill-duesseldorf.de/",
      "map_url": "https://www.google.com/maps/search/?api=1&query=Genki%20Sushi%20Restaurant&query_place_id=ChIJWV7qr4-3uEcRbzeN7aolgo8",
      "source_url": "",
      "phone": "",
      "opening_hours": "",
      "language_support": "",
      "latitude": null,
      "longitude": null,
      "last_reviewed_at": "2026-03-27T23:00:00.000Z",
      "updated_at": "2026-03-27T23:00:00.000Z"
    },
    {
      "id": "ChIJKRtwU4DLuEcRpFmGq4aEEF4",
      "slug": "hitotoki-burghofstrasse",
      "status": "active",
      "name": "Hitotoki Ramen",
      "title": "Hitotoki Ramen",
      "name_ja": "",
      "name_en": "",
      "category": "🌸和食",
      "category1": "🌸和食",
      "detail_category": "🍜ラーメン",
      "category2": "🍜ラーメン",
      "city": "Düsseldorf",
      "region": "Düsseldorf",
      "area": "",
      "address": "Burghofstraße 64, 40223, Düsseldorf",
      "street": "Burghofstraße 64",
      "postcode": "40223",
      "country_code": "DE",
      "short_description": "",
      "description": "",
      "detail_comment": "",
      "description_en": "",
      "tags": "",
      "price": "€10–20",
      "rating": 0,
      "reviews_count": 61,
      "official_url": "",
      "website": "",
      "map_url": "https://www.google.com/maps/search/?api=1&query=Hitotoki%20Ramen&query_place_id=ChIJKRtwU4DLuEcRpFmGq4aEEF4",
      "source_url": "",
      "phone": "",
      "opening_hours": "",
      "language_support": "",
      "latitude": 51.2070209,
      "longitude": 6.770617,
      "last_reviewed_at": "2026-03-27T23:00:00.000Z",
      "updated_at": "2026-03-27T23:00:00.000Z"
    },
    {
      "id": "holy-bahlenstrasse",
      "slug": "holy-bahlenstrasse",
      "status": "active",
      "name": "Holy Rice",
      "title": "Holy Rice",
      "name_ja": "",
      "name_en": "",
      "category": "🌸和食",
      "category1": "🌸和食",
      "detail_category": "🍣寿司",
      "category2": "🍣寿司",
      "city": "Düsseldorf",
      "region": "Düsseldorf",
      "area": "",
      "address": "Bahlenstraße 178-180, 40589, Düsseldorf",
      "street": "Bahlenstraße 178-180",
      "postcode": "40589",
      "country_code": "DE",
      "short_description": "",
      "description": "",
      "detail_comment": "",
      "description_en": "",
      "tags": "",
      "price": "€10–20",
      "rating": 0,
      "reviews_count": 288,
      "official_url": "http://lp-app.com/3118",
      "website": "http://lp-app.com/3118",
      "map_url": "https://www.google.com/maps/search/?api=1&query=Holy%20Rice&query_place_id=ChIJX80wrujLuEcRk4a7aigAs-U",
      "source_url": "",
      "phone": "",
      "opening_hours": "",
      "language_support": "",
      "latitude": null,
      "longitude": null,
      "last_reviewed_at": "2026-03-27T23:00:00.000Z",
      "updated_at": "2026-03-27T23:00:00.000Z"
    },
    {
      "id": "hyuga-kaiserswerther",
      "slug": "hyuga-kaiserswerther",
      "status": "active",
      "name": "Hyuga",
      "title": "Hyuga",
      "name_ja": "",
      "name_en": "",
      "category": "🌸和食",
      "category1": "🌸和食",
      "detail_category": "🍣寿司",
      "category2": "🍣寿司",
      "city": "Düsseldorf",
      "region": "Düsseldorf",
      "area": "",
      "address": "Kaiserswerther Str. 77, 40476, Düsseldorf",
      "street": "Kaiserswerther Str. 77",
      "postcode": "40476",
      "country_code": "DE",
      "short_description": "",
      "description": "",
      "detail_comment": "",
      "description_en": "",
      "tags": "",
      "price": "$$",
      "rating": 0,
      "reviews_count": 697,
      "official_url": "https://www.facebook.com/HyugaDuesseldorf/",
      "website": "https://www.facebook.com/HyugaDuesseldorf/",
      "map_url": "https://www.google.com/maps/search/?api=1&query=Hyuga&query_place_id=ChIJCQZrWyXKuEcReqDbQPGrxfA",
      "source_url": "",
      "phone": "",
      "opening_hours": "",
      "language_support": "",
      "latitude": null,
      "longitude": null,
      "last_reviewed_at": "2026-03-27T23:00:00.000Z",
      "updated_at": "2026-03-27T23:00:00.000Z"
    },
    {
      "id": "ChIJ_VT8I4K3uEcRtbC37aJDWsE",
      "slug": "ishi-hansaallee",
      "status": "active",
      "name": "Ishi Fusion Sushi Restaurant",
      "title": "Ishi Fusion Sushi Restaurant",
      "name_ja": "",
      "name_en": "",
      "category": "🌸和食",
      "category1": "🌸和食",
      "detail_category": "🍣寿司",
      "category2": "🍣寿司",
      "city": "Düsseldorf",
      "region": "Düsseldorf",
      "area": "",
      "address": "Hansaallee 165, 40549, Düsseldorf",
      "street": "Hansaallee 165",
      "postcode": "40549",
      "country_code": "DE",
      "short_description": "",
      "description": "",
      "detail_comment": "",
      "description_en": "",
      "tags": "",
      "price": "",
      "rating": 0,
      "reviews_count": 1190,
      "official_url": "https://www.ishifusionsushirestaurant.de/",
      "website": "https://www.ishifusionsushirestaurant.de/",
      "map_url": "https://www.google.com/maps/search/?api=1&query=Ishi%20Fusion%20Sushi%20Restaurant&query_place_id=ChIJ_VT8I4K3uEcRtbC37aJDWsE",
      "source_url": "",
      "phone": "",
      "opening_hours": "",
      "language_support": "",
      "latitude": 51.23987,
      "longitude": 6.72822,
      "last_reviewed_at": "2026-03-27T23:00:00.000Z",
      "updated_at": "2026-03-27T23:00:00.000Z"
    },
    {
      "id": "ChIJ_YJqLvPLuEcRVW23oOaWrBY",
      "slug": "kenny's-birkenstrasse",
      "status": "active",
      "name": "Kenny's Kitchen",
      "title": "Kenny's Kitchen",
      "name_ja": "",
      "name_en": "",
      "category": "🌸和食",
      "category1": "🌸和食",
      "detail_category": "🍜ラーメン",
      "category2": "🍜ラーメン",
      "city": "Düsseldorf",
      "region": "Düsseldorf",
      "area": "",
      "address": "Birkenstraße 72, 40233, Düsseldorf",
      "street": "Birkenstraße 72",
      "postcode": "40233",
      "country_code": "DE",
      "short_description": "",
      "description": "",
      "detail_comment": "",
      "description_en": "",
      "tags": "",
      "price": "€10–20",
      "rating": 0,
      "reviews_count": 386,
      "official_url": "https://www.instagram.com/kenny.s_kitchen?igsh=Nzl0bWFvYnhzYnlx&utm_source=qr",
      "website": "https://www.instagram.com/kenny.s_kitchen?igsh=Nzl0bWFvYnhzYnlx&utm_source=qr",
      "map_url": "https://www.google.com/maps/search/?api=1&query=Kenny%27s%20Kitchen&query_place_id=ChIJ_YJqLvPLuEcRVW23oOaWrBY",
      "source_url": "",
      "phone": "",
      "opening_hours": "",
      "language_support": "",
      "latitude": 51.2270528,
      "longitude": 6.8058278,
      "last_reviewed_at": "2026-03-27T23:00:00.000Z",
      "updated_at": "2026-03-27T23:00:00.000Z"
    },
    {
      "id": "koi-karl-anton-strasse",
      "slug": "koi-karl-anton-strasse",
      "status": "active",
      "name": "Koi sushi",
      "title": "Koi sushi",
      "name_ja": "",
      "name_en": "",
      "category": "🌸和食",
      "category1": "🌸和食",
      "detail_category": "🍣寿司",
      "category2": "🍣寿司",
      "city": "Düsseldorf",
      "region": "Düsseldorf",
      "area": "",
      "address": "Karl-Anton-Straße 2, 40211, Düsseldorf",
      "street": "Karl-Anton-Straße 2",
      "postcode": "40211",
      "country_code": "DE",
      "short_description": "",
      "description": "",
      "detail_comment": "",
      "description_en": "",
      "tags": "",
      "price": "€20–30",
      "rating": 0,
      "reviews_count": 485,
      "official_url": "http://koi-sushi.jimdosite.com/",
      "website": "http://koi-sushi.jimdosite.com/",
      "map_url": "https://www.google.com/maps/search/?api=1&query=Koi%20sushi&query_place_id=ChIJMfaiGkzLuEcRlV6NthCeSj4",
      "source_url": "",
      "phone": "",
      "opening_hours": "",
      "language_support": "",
      "latitude": null,
      "longitude": null,
      "last_reviewed_at": "2026-03-27T23:00:00.000Z",
      "updated_at": "2026-03-27T23:00:00.000Z"
    },
    {
      "id": "ChIJAQB0-mzKuEcRqkKzo5cM3Ps",
      "slug": "kyodaina-lorettostrasse",
      "status": "active",
      "name": "Kyodaina Poke & Sushi",
      "title": "Kyodaina Poke & Sushi",
      "name_ja": "",
      "name_en": "",
      "category": "🌸和食",
      "category1": "🌸和食",
      "detail_category": "🍣寿司",
      "category2": "🍣寿司",
      "city": "Düsseldorf",
      "region": "Düsseldorf",
      "area": "",
      "address": "Lorettostraße 60, 40219, Düsseldorf",
      "street": "Lorettostraße 60",
      "postcode": "40219",
      "country_code": "DE",
      "short_description": "",
      "description": "",
      "detail_comment": "",
      "description_en": "",
      "tags": "",
      "price": "€20–30",
      "rating": 0,
      "reviews_count": 792,
      "official_url": "http://www.kyodaina.de/",
      "website": "http://www.kyodaina.de/",
      "map_url": "https://www.google.com/maps/search/?api=1&query=Kyodaina%20Poke%20%26%20Sushi&query_place_id=ChIJAQB0-mzKuEcRqkKzo5cM3Ps",
      "source_url": "",
      "phone": "",
      "opening_hours": "",
      "language_support": "",
      "latitude": 51.212477,
      "longitude": 6.764552,
      "last_reviewed_at": "2026-03-27T23:00:00.000Z",
      "updated_at": "2026-03-27T23:00:00.000Z"
    },
    {
      "id": "ChIJ8_ejpcXJuEcRpRz5-TmQdz0",
      "slug": "mai-buscherstrasse",
      "status": "active",
      "name": "Mai Sushi and More",
      "title": "Mai Sushi and More",
      "name_ja": "",
      "name_en": "",
      "category": "🌸和食",
      "category1": "🌸和食",
      "detail_category": "🍣寿司",
      "category2": "🍣寿司",
      "city": "Düsseldorf",
      "region": "Düsseldorf",
      "area": "",
      "address": "Buscherstraße 4, 40239, Düsseldorf",
      "street": "Buscherstraße 4",
      "postcode": "40239",
      "country_code": "DE",
      "short_description": "",
      "description": "",
      "detail_comment": "",
      "description_en": "",
      "tags": "",
      "price": "€20–30",
      "rating": 0,
      "reviews_count": 167,
      "official_url": "http://mai-sushi-and-more.eatbu.com/",
      "website": "http://mai-sushi-and-more.eatbu.com/",
      "map_url": "https://www.google.com/maps/search/?api=1&query=Mai%20Sushi%20and%20More&query_place_id=ChIJ8_ejpcXJuEcRpRz5-TmQdz0",
      "source_url": "",
      "phone": "",
      "opening_hours": "",
      "language_support": "",
      "latitude": 51.2478251,
      "longitude": 6.7974845,
      "last_reviewed_at": "2026-03-27T23:00:00.000Z",
      "updated_at": "2026-03-27T23:00:00.000Z"
    },
    {
      "id": "maruyasu-immermannstrasse",
      "slug": "maruyasu-immermannstrasse",
      "status": "active",
      "name": "Maruyasu Immermann",
      "title": "Maruyasu Immermann",
      "name_ja": "",
      "name_en": "",
      "category": "🌸和食",
      "category1": "🌸和食",
      "detail_category": "🍣寿司",
      "category2": "🍣寿司",
      "city": "Düsseldorf",
      "region": "Düsseldorf",
      "area": "",
      "address": "Immermannstraße 11, 40210, Düsseldorf",
      "street": "Immermannstraße 11",
      "postcode": "40210",
      "country_code": "DE",
      "short_description": "",
      "description": "",
      "detail_comment": "",
      "description_en": "",
      "tags": "",
      "price": "€10–20",
      "rating": 0,
      "reviews_count": 1674,
      "official_url": "http://maruyasu-de.jimdoweb.com/",
      "website": "http://maruyasu-de.jimdoweb.com/",
      "map_url": "https://www.google.com/maps/search/?api=1&query=Maruyasu%20Immermann&query_place_id=ChIJEwTk0jrKuEcRYYz6_qf74_w",
      "source_url": "",
      "phone": "",
      "opening_hours": "",
      "language_support": "",
      "latitude": null,
      "longitude": null,
      "last_reviewed_at": "2026-03-27T23:00:00.000Z",
      "updated_at": "2026-03-27T23:00:00.000Z"
    },
    {
      "id": "ChIJ6c_JIADLuEcRlPKsNOCyvi0",
      "slug": "may-derendorfer",
      "status": "active",
      "name": "May Sushi & More",
      "title": "May Sushi & More",
      "name_ja": "",
      "name_en": "",
      "category": "🌸和食",
      "category1": "🌸和食",
      "detail_category": "🍣寿司",
      "category2": "🍣寿司",
      "city": "Düsseldorf",
      "region": "Düsseldorf",
      "area": "",
      "address": "Derendorfer Str. 100, 40479, Düsseldorf",
      "street": "Derendorfer Str. 100",
      "postcode": "40479",
      "country_code": "DE",
      "short_description": "",
      "description": "",
      "detail_comment": "",
      "description_en": "",
      "tags": "",
      "price": "",
      "rating": 0,
      "reviews_count": 0,
      "official_url": "",
      "website": "",
      "map_url": "https://www.google.com/maps/search/?api=1&query=May%20Sushi%20%26%20More&query_place_id=ChIJ6c_JIADLuEcRlPKsNOCyvi0",
      "source_url": "",
      "phone": "",
      "opening_hours": "",
      "language_support": "",
      "latitude": 51.2330621,
      "longitude": 6.7903113,
      "last_reviewed_at": "2026-03-27T23:00:00.000Z",
      "updated_at": "2026-03-27T23:00:00.000Z"
    },
    {
      "id": "nagomi-bismarckstrasse",
      "slug": "nagomi-bismarckstrasse",
      "status": "active",
      "name": "Nagomi - Japanese Restaurant",
      "title": "Nagomi - Japanese Restaurant",
      "name_ja": "",
      "name_en": "",
      "category": "🌸和食",
      "category1": "🌸和食",
      "detail_category": "🍣寿司",
      "category2": "🍣寿司",
      "city": "Düsseldorf",
      "region": "Düsseldorf",
      "area": "",
      "address": "Bismarckstraße 53, 40210, Düsseldorf",
      "street": "Bismarckstraße 53",
      "postcode": "40210",
      "country_code": "DE",
      "short_description": "",
      "description": "",
      "detail_comment": "",
      "description_en": "",
      "tags": "",
      "price": "$$$",
      "rating": 0,
      "reviews_count": 1034,
      "official_url": "http://nagomi.de/",
      "website": "http://nagomi.de/",
      "map_url": "https://www.google.com/maps/search/?api=1&query=Nagomi%20-%20Japanese%20Restaurant&query_place_id=ChIJTS7J-jrKuEcRHi4yXS-PWX0",
      "source_url": "",
      "phone": "",
      "opening_hours": "",
      "language_support": "",
      "latitude": null,
      "longitude": null,
      "last_reviewed_at": "2026-03-27T23:00:00.000Z",
      "updated_at": "2026-03-27T23:00:00.000Z"
    },
    {
      "id": "ChIJ6ToCPyXKuEcREwbUY_G-kqU",
      "slug": "naniwa-oststrasse",
      "status": "active",
      "name": "Naniwa Noodles & Soups",
      "title": "Naniwa Noodles & Soups",
      "name_ja": "",
      "name_en": "",
      "category": "🌸和食",
      "category1": "🌸和食",
      "detail_category": "🍜ラーメン",
      "category2": "🍜ラーメン",
      "city": "Düsseldorf",
      "region": "Düsseldorf",
      "area": "",
      "address": "Oststraße 55, 40211, Düsseldorf",
      "street": "Oststraße 55",
      "postcode": "40211",
      "country_code": "DE",
      "short_description": "",
      "description": "",
      "detail_comment": "",
      "description_en": "",
      "tags": "",
      "price": "€10–20",
      "rating": 0,
      "reviews_count": 5150,
      "official_url": "http://www.naniwa.de/",
      "website": "http://www.naniwa.de/",
      "map_url": "https://www.google.com/maps/search/?api=1&query=Naniwa%20Noodles%20%26%20Soups&query_place_id=ChIJ6ToCPyXKuEcREwbUY_G-kqU",
      "source_url": "",
      "phone": "",
      "opening_hours": "",
      "language_support": "",
      "latitude": 51.2249515,
      "longitude": 6.7881079,
      "last_reviewed_at": "2026-03-27T23:00:00.000Z",
      "updated_at": "2026-03-27T23:00:00.000Z"
    },
    {
      "id": "ChIJ4Q4qkPHLuEcR3Xob0nJz4Yg",
      "slug": "narumi-bilker",
      "status": "active",
      "name": "Narumi Sushi & Japanische Küche",
      "title": "Narumi Sushi & Japanische Küche",
      "name_ja": "",
      "name_en": "",
      "category": "🌸和食",
      "category1": "🌸和食",
      "detail_category": "🍣寿司",
      "category2": "🍣寿司",
      "city": "Düsseldorf",
      "region": "Düsseldorf",
      "area": "",
      "address": "Bilker Allee 79, 40219, Düsseldorf",
      "street": "Bilker Allee 79",
      "postcode": "40219",
      "country_code": "DE",
      "short_description": "",
      "description": "",
      "detail_comment": "",
      "description_en": "",
      "tags": "",
      "price": "€10–20",
      "rating": 0,
      "reviews_count": 95,
      "official_url": "https://www.narumisushi.de/",
      "website": "https://www.narumisushi.de/",
      "map_url": "https://www.google.com/maps/search/?api=1&query=Narumi%20Sushi%20%26%20Japanische%20K%C3%BCche&query_place_id=ChIJ4Q4qkPHLuEcR3Xob0nJz4Yg",
      "source_url": "",
      "phone": "",
      "opening_hours": "",
      "language_support": "",
      "latitude": 51.210671,
      "longitude": 6.7688589,
      "last_reviewed_at": "2026-03-27T23:00:00.000Z",
      "updated_at": "2026-03-27T23:00:00.000Z"
    },
    {
      "id": "narumi-hüttenstrasse",
      "slug": "narumi-hüttenstrasse",
      "status": "active",
      "name": "Narumi Sushi & Ramen",
      "title": "Narumi Sushi & Ramen",
      "name_ja": "",
      "name_en": "",
      "category": "🌸和食",
      "category1": "🌸和食",
      "detail_category": "🍣寿司",
      "category2": "🍣寿司",
      "city": "Düsseldorf",
      "region": "Düsseldorf",
      "area": "",
      "address": "Hüttenstraße 83, 40215, Düsseldorf",
      "street": "Hüttenstraße 83",
      "postcode": "40215",
      "country_code": "DE",
      "short_description": "",
      "description": "",
      "detail_comment": "",
      "description_en": "",
      "tags": "",
      "price": "€10–20",
      "rating": 0,
      "reviews_count": 429,
      "official_url": "https://www.narumisushi.de/",
      "website": "https://www.narumisushi.de/",
      "map_url": "https://www.google.com/maps/search/?api=1&query=Narumi%20Sushi%20%26%20Ramen&query_place_id=ChIJDzmp5gnLuEcRXc6RJHGmZb0",
      "source_url": "",
      "phone": "",
      "opening_hours": "",
      "language_support": "",
      "latitude": null,
      "longitude": null,
      "last_reviewed_at": "2026-03-27T23:00:00.000Z",
      "updated_at": "2026-03-27T23:00:00.000Z"
    },
    {
      "id": "ChIJ2fhcbFHKuEcRixwMY2p_LZ4",
      "slug": "oishii-moorenstrasse",
      "status": "active",
      "name": "Oishii Sushi & More",
      "title": "Oishii Sushi & More",
      "name_ja": "",
      "name_en": "",
      "category": "🌸和食",
      "category1": "🌸和食",
      "detail_category": "🍣寿司",
      "category2": "🍣寿司",
      "city": "Düsseldorf",
      "region": "Düsseldorf",
      "area": "",
      "address": "Moorenstraße 78, 40225, Düsseldorf",
      "street": "Moorenstraße 78",
      "postcode": "40225",
      "country_code": "DE",
      "short_description": "",
      "description": "",
      "detail_comment": "",
      "description_en": "",
      "tags": "",
      "price": "€10–20",
      "rating": 0,
      "reviews_count": 234,
      "official_url": "http://www.oishii-duesseldorf.de/",
      "website": "http://www.oishii-duesseldorf.de/",
      "map_url": "https://www.google.com/maps/search/?api=1&query=Oishii%20Sushi%20%26%20More&query_place_id=ChIJ2fhcbFHKuEcRixwMY2p_LZ4",
      "source_url": "",
      "phone": "",
      "opening_hours": "",
      "language_support": "",
      "latitude": 51.1992374,
      "longitude": 6.7889966,
      "last_reviewed_at": "2026-03-27T23:00:00.000Z",
      "updated_at": "2026-03-27T23:00:00.000Z"
    },
    {
      "id": "opin-grafenberger",
      "slug": "opin-grafenberger",
      "status": "active",
      "name": "OPIN SUSHI",
      "title": "OPIN SUSHI",
      "name_ja": "",
      "name_en": "",
      "category": "🌸和食",
      "category1": "🌸和食",
      "detail_category": "🍣寿司",
      "category2": "🍣寿司",
      "city": "Düsseldorf",
      "region": "Düsseldorf",
      "area": "",
      "address": "Grafenberger Allee 257, 40237, Düsseldorf",
      "street": "Grafenberger Allee 257",
      "postcode": "40237",
      "country_code": "DE",
      "short_description": "",
      "description": "",
      "detail_comment": "",
      "description_en": "",
      "tags": "",
      "price": "",
      "rating": 0,
      "reviews_count": 531,
      "official_url": "http://www.opin-engerhof.de/",
      "website": "http://www.opin-engerhof.de/",
      "map_url": "https://www.google.com/maps/search/?api=1&query=OPIN%20SUSHI&query_place_id=ChIJr9NOXmPJuEcRKfGUAtAlyMc",
      "source_url": "",
      "phone": "",
      "opening_hours": "",
      "language_support": "",
      "latitude": null,
      "longitude": null,
      "last_reviewed_at": "2026-03-27T23:00:00.000Z",
      "updated_at": "2026-03-27T23:00:00.000Z"
    },
    {
      "id": "ChIJU_-ws9LLuEcRxWOkoc1A3jg",
      "slug": "ramen-kölner",
      "status": "active",
      "name": "Ramen King Wersten",
      "title": "Ramen King Wersten",
      "name_ja": "",
      "name_en": "",
      "category": "🌸和食",
      "category1": "🌸和食",
      "detail_category": "🍜ラーメン",
      "category2": "🍜ラーメン",
      "city": "Düsseldorf",
      "region": "Düsseldorf",
      "area": "",
      "address": "Kölner Landstraße 285, 40589, Düsseldorf",
      "street": "Kölner Landstraße 285",
      "postcode": "40589",
      "country_code": "DE",
      "short_description": "",
      "description": "",
      "detail_comment": "",
      "description_en": "",
      "tags": "",
      "price": "€10–20",
      "rating": 0,
      "reviews_count": 49,
      "official_url": "https://www.ramen-king-duesseldorf.de/",
      "website": "https://www.ramen-king-duesseldorf.de/",
      "map_url": "https://www.google.com/maps/search/?api=1&query=Ramen%20King%20Wersten&query_place_id=ChIJU_-ws9LLuEcRxWOkoc1A3jg",
      "source_url": "",
      "phone": "",
      "opening_hours": "",
      "language_support": "",
      "latitude": 51.1831282,
      "longitude": 6.8221724,
      "last_reviewed_at": "2026-03-27T23:00:00.000Z",
      "updated_at": "2026-03-27T23:00:00.000Z"
    },
    {
      "id": "ramen-franklinstrasse",
      "slug": "ramen-franklinstrasse",
      "status": "active",
      "name": "Ramen Soul",
      "title": "Ramen Soul",
      "name_ja": "",
      "name_en": "",
      "category": "🌸和食",
      "category1": "🌸和食",
      "detail_category": "🍜ラーメン",
      "category2": "🍜ラーメン",
      "city": "Düsseldorf",
      "region": "Düsseldorf",
      "area": "",
      "address": "Franklinstraße 24, 40479, Düsseldorf",
      "street": "Franklinstraße 24",
      "postcode": "40479",
      "country_code": "DE",
      "short_description": "",
      "description": "",
      "detail_comment": "",
      "description_en": "",
      "tags": "",
      "price": "€10–20",
      "rating": 0,
      "reviews_count": 881,
      "official_url": "http://www.ramensoul.de/",
      "website": "http://www.ramensoul.de/",
      "map_url": "https://www.google.com/maps/search/?api=1&query=Ramen%20Soul&query_place_id=ChIJv5xFTIjJuEcRC7xxUbivLmw",
      "source_url": "",
      "phone": "",
      "opening_hours": "",
      "language_support": "",
      "latitude": null,
      "longitude": null,
      "last_reviewed_at": "2026-03-27T23:00:00.000Z",
      "updated_at": "2026-03-27T23:00:00.000Z"
    },
    {
      "id": "ramen-rossstrasse",
      "slug": "ramen-rossstrasse",
      "status": "active",
      "name": "Ramen Soul 2",
      "title": "Ramen Soul 2",
      "name_ja": "",
      "name_en": "",
      "category": "🌸和食",
      "category1": "🌸和食",
      "detail_category": "🍜ラーメン",
      "category2": "🍜ラーメン",
      "city": "Düsseldorf",
      "region": "Düsseldorf",
      "area": "",
      "address": "Roßstraße 87, 40476, Düsseldorf",
      "street": "Roßstraße 87",
      "postcode": "40476",
      "country_code": "DE",
      "short_description": "",
      "description": "",
      "detail_comment": "",
      "description_en": "",
      "tags": "",
      "price": "€10–20",
      "rating": 0,
      "reviews_count": 440,
      "official_url": "http://www.ramensoul.de/",
      "website": "http://www.ramensoul.de/",
      "map_url": "https://www.google.com/maps/search/?api=1&query=Ramen%20Soul%202&query_place_id=ChIJH1s-VxvJuEcRbPtTONY5sjM",
      "source_url": "",
      "phone": "",
      "opening_hours": "",
      "language_support": "",
      "latitude": null,
      "longitude": null,
      "last_reviewed_at": "2026-03-27T23:00:00.000Z",
      "updated_at": "2026-03-27T23:00:00.000Z"
    },
    {
      "id": "ChIJw63vCbnLuEcRu0KWUHowNPE",
      "slug": "ramen-liefergasse",
      "status": "active",
      "name": "Ramen Soul 4 (Altstadt)",
      "title": "Ramen Soul 4 (Altstadt)",
      "name_ja": "",
      "name_en": "",
      "category": "🌸和食",
      "category1": "🌸和食",
      "detail_category": "🍜ラーメン",
      "category2": "🍜ラーメン",
      "city": "Düsseldorf",
      "region": "Düsseldorf",
      "area": "",
      "address": "Liefergasse 7, 40213, Düsseldorf",
      "street": "Liefergasse 7",
      "postcode": "40213",
      "country_code": "DE",
      "short_description": "",
      "description": "",
      "detail_comment": "",
      "description_en": "",
      "tags": "",
      "price": "€10–20",
      "rating": 0,
      "reviews_count": 183,
      "official_url": "https://www.ramensoul.de/",
      "website": "https://www.ramensoul.de/",
      "map_url": "https://www.google.com/maps/search/?api=1&query=Ramen%20Soul%204%20(Altstadt)&query_place_id=ChIJw63vCbnLuEcRu0KWUHowNPE",
      "source_url": "",
      "phone": "",
      "opening_hours": "",
      "language_support": "",
      "latitude": 51.2283167,
      "longitude": 6.7732659,
      "last_reviewed_at": "2026-03-27T23:00:00.000Z",
      "updated_at": "2026-03-27T23:00:00.000Z"
    },
    {
      "id": "ChIJXdbnls_LuEcRWhsWBF4WgsA",
      "slug": "ramen-bilker",
      "status": "active",
      "name": "Ramen Takezo Bilker Allee",
      "title": "Ramen Takezo Bilker Allee",
      "name_ja": "",
      "name_en": "",
      "category": "🌸和食",
      "category1": "🌸和食",
      "detail_category": "🍜ラーメン",
      "category2": "🍜ラーメン",
      "city": "Düsseldorf",
      "region": "Düsseldorf",
      "area": "",
      "address": "Bilker Allee 56, 40219, Düsseldorf",
      "street": "Bilker Allee 56",
      "postcode": "40219",
      "country_code": "DE",
      "short_description": "",
      "description": "",
      "detail_comment": "",
      "description_en": "",
      "tags": "",
      "price": "€10–20",
      "rating": 0,
      "reviews_count": 1641,
      "official_url": "https://www.instagram.com/ramen_takezo.bilkerallee/",
      "website": "https://www.instagram.com/ramen_takezo.bilkerallee/",
      "map_url": "https://www.google.com/maps/search/?api=1&query=Ramen%20Takezo%20Bilker%20Allee&query_place_id=ChIJXdbnls_LuEcRWhsWBF4WgsA",
      "source_url": "",
      "phone": "",
      "opening_hours": "",
      "language_support": "",
      "latitude": 51.2110042,
      "longitude": 6.7679928,
      "last_reviewed_at": "2026-03-27T23:00:00.000Z",
      "updated_at": "2026-03-27T23:00:00.000Z"
    },
    {
      "id": "renya-collenbachstrasse",
      "slug": "renya-collenbachstrasse",
      "status": "active",
      "name": "Renya",
      "title": "Renya",
      "name_ja": "",
      "name_en": "",
      "category": "🌸和食",
      "category1": "🌸和食",
      "detail_category": "🍣寿司",
      "category2": "🍣寿司",
      "city": "Düsseldorf",
      "region": "Düsseldorf",
      "area": "",
      "address": "Collenbachstraße 1, 40476, Düsseldorf",
      "street": "Collenbachstraße 1",
      "postcode": "40476",
      "country_code": "DE",
      "short_description": "",
      "description": "",
      "detail_comment": "",
      "description_en": "",
      "tags": "",
      "price": "€20–30",
      "rating": 0,
      "reviews_count": 335,
      "official_url": "http://renya2015.com/",
      "website": "http://renya2015.com/",
      "map_url": "https://www.google.com/maps/search/?api=1&query=Renya&query_place_id=ChIJDR6nv4zJuEcRTsuV7pY54Xo",
      "source_url": "",
      "phone": "",
      "opening_hours": "",
      "language_support": "",
      "latitude": null,
      "longitude": null,
      "last_reviewed_at": "2026-03-27T23:00:00.000Z",
      "updated_at": "2026-03-27T23:00:00.000Z"
    },
    {
      "id": "restaurant-weseler",
      "slug": "restaurant-weseler",
      "status": "active",
      "name": "Restaurant Combo",
      "title": "Restaurant Combo",
      "name_ja": "",
      "name_en": "",
      "category": "🌸和食",
      "category1": "🌸和食",
      "detail_category": "🍣寿司",
      "category2": "🍣寿司",
      "city": "Düsseldorf",
      "region": "Düsseldorf",
      "area": "",
      "address": "Weseler Str. 35, 40239, Düsseldorf",
      "street": "Weseler Str. 35",
      "postcode": "40239",
      "country_code": "DE",
      "short_description": "",
      "description": "",
      "detail_comment": "",
      "description_en": "",
      "tags": "",
      "price": "$$",
      "rating": 0,
      "reviews_count": 174,
      "official_url": "http://www.restaurant-combo.de/",
      "website": "http://www.restaurant-combo.de/",
      "map_url": "https://www.google.com/maps/search/?api=1&query=Restaurant%20Combo&query_place_id=ChIJP_KcXZLJuEcRdK0lR3B18SE",
      "source_url": "",
      "phone": "",
      "opening_hours": "",
      "language_support": "",
      "latitude": null,
      "longitude": null,
      "last_reviewed_at": "2026-03-27T23:00:00.000Z",
      "updated_at": "2026-03-27T23:00:00.000Z"
    },
    {
      "id": "restaurant-hohenzollernallee",
      "slug": "restaurant-hohenzollernallee",
      "status": "active",
      "name": "Restaurant DEN",
      "title": "Restaurant DEN",
      "name_ja": "",
      "name_en": "",
      "category": "🌸和食",
      "category1": "🌸和食",
      "detail_category": "🍣寿司",
      "category2": "🍣寿司",
      "city": "Düsseldorf",
      "region": "Düsseldorf",
      "area": "",
      "address": "Hohenzollernallee 8d, 40235, Düsseldorf",
      "street": "Hohenzollernallee 8d",
      "postcode": "40235",
      "country_code": "DE",
      "short_description": "",
      "description": "",
      "detail_comment": "",
      "description_en": "",
      "tags": "",
      "price": "$$$",
      "rating": 0,
      "reviews_count": 1076,
      "official_url": "http://www.denrestaurant.de/",
      "website": "http://www.denrestaurant.de/",
      "map_url": "https://www.google.com/maps/search/?api=1&query=Restaurant%20DEN&query_place_id=ChIJKwfz_AzJuEcRMXLpsW1wK64",
      "source_url": "",
      "phone": "",
      "opening_hours": "",
      "language_support": "",
      "latitude": null,
      "longitude": null,
      "last_reviewed_at": "2026-03-27T23:00:00.000Z",
      "updated_at": "2026-03-27T23:00:00.000Z"
    },
    {
      "id": "rika-gehrtsstrasse",
      "slug": "rika-gehrtsstrasse",
      "status": "active",
      "name": "Rika",
      "title": "Rika",
      "name_ja": "",
      "name_en": "",
      "category": "🌸和食",
      "category1": "🌸和食",
      "detail_category": "🍜ラーメン",
      "category2": "🍜ラーメン",
      "city": "Düsseldorf",
      "region": "Düsseldorf",
      "area": "",
      "address": "Gehrtsstraße 16, 40235, Düsseldorf",
      "street": "Gehrtsstraße 16",
      "postcode": "40235",
      "country_code": "DE",
      "short_description": "",
      "description": "",
      "detail_comment": "",
      "description_en": "",
      "tags": "",
      "price": "€10–20",
      "rating": 0,
      "reviews_count": 310,
      "official_url": "",
      "website": "",
      "map_url": "https://www.google.com/maps/search/?api=1&query=Rika&query_place_id=ChIJGYl0V2TJuEcRWRuq6p0WruE",
      "source_url": "",
      "phone": "",
      "opening_hours": "",
      "language_support": "",
      "latitude": null,
      "longitude": null,
      "last_reviewed_at": "2026-03-27T23:00:00.000Z",
      "updated_at": "2026-03-27T23:00:00.000Z"
    },
    {
      "id": "sabi-luegallee",
      "slug": "sabi-luegallee",
      "status": "active",
      "name": "SABI & GARI",
      "title": "SABI & GARI",
      "name_ja": "",
      "name_en": "",
      "category": "🌸和食",
      "category1": "🌸和食",
      "detail_category": "🍣寿司",
      "category2": "🍣寿司",
      "city": "Düsseldorf",
      "region": "Düsseldorf",
      "area": "",
      "address": "Luegallee 13, 40545, Düsseldorf",
      "street": "Luegallee 13",
      "postcode": "40545",
      "country_code": "DE",
      "short_description": "",
      "description": "",
      "detail_comment": "",
      "description_en": "",
      "tags": "",
      "price": "",
      "rating": 0,
      "reviews_count": 169,
      "official_url": "https://sabigari.de/de/",
      "website": "https://sabigari.de/de/",
      "map_url": "https://www.google.com/maps/search/?api=1&query=SABI%20%26%20GARI&query_place_id=ChIJfzBd-wPKuEcRnL8NRdDob6Q",
      "source_url": "",
      "phone": "",
      "opening_hours": "",
      "language_support": "",
      "latitude": null,
      "longitude": null,
      "last_reviewed_at": "2026-03-27T23:00:00.000Z",
      "updated_at": "2026-03-27T23:00:00.000Z"
    },
    {
      "id": "ChIJzX9UWnK1uEcRoA492KcO6E0",
      "slug": "sakuragiya-luegallee",
      "status": "active",
      "name": "Sakuragiya - Japanese Ramen",
      "title": "Sakuragiya - Japanese Ramen",
      "name_ja": "",
      "name_en": "",
      "category": "🌸和食",
      "category1": "🌸和食",
      "detail_category": "🍜ラーメン",
      "category2": "🍜ラーメン",
      "city": "Düsseldorf",
      "region": "Düsseldorf",
      "area": "",
      "address": "Luegallee 118, 40545, Düsseldorf",
      "street": "Luegallee 118",
      "postcode": "40545",
      "country_code": "DE",
      "short_description": "",
      "description": "",
      "detail_comment": "",
      "description_en": "",
      "tags": "",
      "price": "€10–20",
      "rating": 0,
      "reviews_count": 388,
      "official_url": "https://www.instagram.com/sakuragiya118/",
      "website": "https://www.instagram.com/sakuragiya118/",
      "map_url": "https://www.google.com/maps/search/?api=1&query=Sakuragiya%20-%20Japanese%20Ramen&query_place_id=ChIJzX9UWnK1uEcRoA492KcO6E0",
      "source_url": "",
      "phone": "",
      "opening_hours": "",
      "language_support": "",
      "latitude": 51.2317192,
      "longitude": 6.7494351,
      "last_reviewed_at": "2026-03-27T23:00:00.000Z",
      "updated_at": "2026-03-27T23:00:00.000Z"
    },
    {
      "id": "shinju-fürstenwall",
      "slug": "shinju-fürstenwall",
      "status": "active",
      "name": "Shinju Sushi&Grill",
      "title": "Shinju Sushi&Grill",
      "name_ja": "",
      "name_en": "",
      "category": "🌸和食",
      "category1": "🌸和食",
      "detail_category": "🍣寿司",
      "category2": "🍣寿司",
      "city": "Düsseldorf",
      "region": "Düsseldorf",
      "area": "",
      "address": "Fürstenwall 120, 40217, Düsseldorf",
      "street": "Fürstenwall 120",
      "postcode": "40217",
      "country_code": "DE",
      "short_description": "",
      "description": "",
      "detail_comment": "",
      "description_en": "",
      "tags": "",
      "price": "",
      "rating": 0,
      "reviews_count": 384,
      "official_url": "https://shinjuduesseldorf.de/",
      "website": "https://shinjuduesseldorf.de/",
      "map_url": "https://www.google.com/maps/search/?api=1&query=Shinju%20Sushi%26Grill&query_place_id=ChIJT7rrDS7LuEcRq-pNsEXihYg",
      "source_url": "",
      "phone": "",
      "opening_hours": "",
      "language_support": "",
      "latitude": null,
      "longitude": null,
      "last_reviewed_at": "2026-03-27T23:00:00.000Z",
      "updated_at": "2026-03-27T23:00:00.000Z"
    },
    {
      "id": "soupday-bismarckstrasse",
      "slug": "soupday-bismarckstrasse",
      "status": "active",
      "name": "Soupday",
      "title": "Soupday",
      "name_ja": "",
      "name_en": "",
      "category": "🌸和食",
      "category1": "🌸和食",
      "detail_category": "🍜ラーメン",
      "category2": "🍜ラーメン",
      "city": "Düsseldorf",
      "region": "Düsseldorf",
      "area": "",
      "address": "Bismarckstraße 54A, 40210, Düsseldorf",
      "street": "Bismarckstraße 54A",
      "postcode": "40210",
      "country_code": "DE",
      "short_description": "",
      "description": "",
      "detail_comment": "",
      "description_en": "",
      "tags": "",
      "price": "€10–20",
      "rating": 0,
      "reviews_count": 892,
      "official_url": "",
      "website": "",
      "map_url": "https://www.google.com/maps/search/?api=1&query=Soupday&query_place_id=ChIJmdggO7zLuEcRJVyW5DnNs6o",
      "source_url": "",
      "phone": "",
      "opening_hours": "",
      "language_support": "",
      "latitude": null,
      "longitude": null,
      "last_reviewed_at": "2026-03-27T23:00:00.000Z",
      "updated_at": "2026-03-27T23:00:00.000Z"
    },
    {
      "id": "sumi.-schinkelstrasse",
      "slug": "sumi.-schinkelstrasse",
      "status": "active",
      "name": "sumi.",
      "title": "sumi.",
      "name_ja": "",
      "name_en": "",
      "category": "🌸和食",
      "category1": "🌸和食",
      "detail_category": "🍣寿司",
      "category2": "🍣寿司",
      "city": "Düsseldorf",
      "region": "Düsseldorf",
      "area": "",
      "address": "Schinkelstraße 28, 40211, Düsseldorf",
      "street": "Schinkelstraße 28",
      "postcode": "40211",
      "country_code": "DE",
      "short_description": "",
      "description": "",
      "detail_comment": "",
      "description_en": "",
      "tags": "",
      "price": "$$",
      "rating": 0,
      "reviews_count": 667,
      "official_url": "https://sumi.chimzgmbh.com/",
      "website": "https://sumi.chimzgmbh.com/",
      "map_url": "https://www.google.com/maps/search/?api=1&query=sumi.&query_place_id=ChIJVZ0YZCjKuEcRF11wGDlXSWI",
      "source_url": "",
      "phone": "",
      "opening_hours": "",
      "language_support": "",
      "latitude": null,
      "longitude": null,
      "last_reviewed_at": "2026-03-27T23:00:00.000Z",
      "updated_at": "2026-03-27T23:00:00.000Z"
    },
    {
      "id": "sushi-schlüterstrasse",
      "slug": "sushi-schlüterstrasse",
      "status": "active",
      "name": "Sushi Daily",
      "title": "Sushi Daily",
      "name_ja": "",
      "name_en": "",
      "category": "🌸和食",
      "category1": "🌸和食",
      "detail_category": "🍣寿司",
      "category2": "🍣寿司",
      "city": "Düsseldorf",
      "region": "Düsseldorf",
      "area": "",
      "address": "Schlüterstraße 3b, 40235, Düsseldorf",
      "street": "Schlüterstraße 3b",
      "postcode": "40235",
      "country_code": "DE",
      "short_description": "",
      "description": "",
      "detail_comment": "",
      "description_en": "",
      "tags": "",
      "price": "€10–20",
      "rating": 0,
      "reviews_count": 12,
      "official_url": "http://www.sushidaily.de/?utm_source=google&utm_medium=local&utm_content=DE&utm_term=DE0012",
      "website": "http://www.sushidaily.de/?utm_source=google&utm_medium=local&utm_content=DE&utm_term=DE0012",
      "map_url": "https://www.google.com/maps/search/?api=1&query=Sushi%20Daily&query_place_id=ChIJeS3id2PJuEcRoV2QZTEwOng",
      "source_url": "",
      "phone": "",
      "opening_hours": "",
      "language_support": "",
      "latitude": null,
      "longitude": null,
      "last_reviewed_at": "2026-03-27T23:00:00.000Z",
      "updated_at": "2026-03-27T23:00:00.000Z"
    },
    {
      "id": "ChIJb4UpwFbJuEcR_qzrfnjxTQM",
      "slug": "sushi-duisburger",
      "status": "active",
      "name": "Sushi Han",
      "title": "Sushi Han",
      "name_ja": "",
      "name_en": "",
      "category": "🌸和食",
      "category1": "🌸和食",
      "detail_category": "🍣寿司",
      "category2": "🍣寿司",
      "city": "Düsseldorf",
      "region": "Düsseldorf",
      "area": "",
      "address": "Duisburger Str. 16, 40477, Düsseldorf",
      "street": "Duisburger Str. 16",
      "postcode": "40477",
      "country_code": "DE",
      "short_description": "",
      "description": "",
      "detail_comment": "",
      "description_en": "",
      "tags": "",
      "price": "€10–20",
      "rating": 0,
      "reviews_count": 39,
      "official_url": "https://sushihan.eatbu.com/?lang=de",
      "website": "https://sushihan.eatbu.com/?lang=de",
      "map_url": "https://www.google.com/maps/search/?api=1&query=Sushi%20Han&query_place_id=ChIJb4UpwFbJuEcR_qzrfnjxTQM",
      "source_url": "",
      "phone": "",
      "opening_hours": "",
      "language_support": "",
      "latitude": 51.2366495,
      "longitude": 6.7806004,
      "last_reviewed_at": "2026-03-27T23:00:00.000Z",
      "updated_at": "2026-03-27T23:00:00.000Z"
    },
    {
      "id": "sushi-nikolaus-knopp-platz",
      "slug": "sushi-nikolaus-knopp-platz",
      "status": "active",
      "name": "Sushi Kaiser Düsseldorf",
      "title": "Sushi Kaiser Düsseldorf",
      "name_ja": "",
      "name_en": "",
      "category": "🌸和食",
      "category1": "🌸和食",
      "detail_category": "🍣寿司",
      "category2": "🍣寿司",
      "city": "Düsseldorf",
      "region": "Düsseldorf",
      "area": "",
      "address": "Nikolaus-Knopp-Platz 37, 40549, Düsseldorf",
      "street": "Nikolaus-Knopp-Platz 37",
      "postcode": "40549",
      "country_code": "DE",
      "short_description": "",
      "description": "",
      "detail_comment": "",
      "description_en": "",
      "tags": "",
      "price": "€10–20",
      "rating": 0,
      "reviews_count": 233,
      "official_url": "",
      "website": "",
      "map_url": "https://www.google.com/maps/search/?api=1&query=Sushi%20Kaiser%20D%C3%BCsseldorf&query_place_id=ChIJP-fEF9y1uEcRrqbsHT-6-mY",
      "source_url": "",
      "phone": "",
      "opening_hours": "",
      "language_support": "",
      "latitude": null,
      "longitude": null,
      "last_reviewed_at": "2026-03-27T23:00:00.000Z",
      "updated_at": "2026-03-27T23:00:00.000Z"
    },
    {
      "id": "sushi-emil-barth-strasse",
      "slug": "sushi-emil-barth-strasse",
      "status": "active",
      "name": "Sushi Palace Düsseldorf",
      "title": "Sushi Palace Düsseldorf",
      "name_ja": "",
      "name_en": "",
      "category": "🌸和食",
      "category1": "🌸和食",
      "detail_category": "🍣寿司",
      "category2": "🍣寿司",
      "city": "Düsseldorf",
      "region": "Düsseldorf",
      "area": "",
      "address": "Emil-Barth-Straße 21, 40595, Düsseldorf",
      "street": "Emil-Barth-Straße 21",
      "postcode": "40595",
      "country_code": "DE",
      "short_description": "",
      "description": "",
      "detail_comment": "",
      "description_en": "",
      "tags": "",
      "price": "€10–20",
      "rating": 0,
      "reviews_count": 54,
      "official_url": "http://sushi-palace.com/",
      "website": "http://sushi-palace.com/",
      "map_url": "https://www.google.com/maps/search/?api=1&query=Sushi%20Palace%20D%C3%BCsseldorf&query_place_id=ChIJrfRtd9czv0cR2KsFoxg5t-k",
      "source_url": "",
      "phone": "",
      "opening_hours": "",
      "language_support": "",
      "latitude": null,
      "longitude": null,
      "last_reviewed_at": "2026-03-27T23:00:00.000Z",
      "updated_at": "2026-03-27T23:00:00.000Z"
    },
    {
      "id": "sushi-münsterstrasse",
      "slug": "sushi-münsterstrasse",
      "status": "active",
      "name": "Sushi Takushi",
      "title": "Sushi Takushi",
      "name_ja": "",
      "name_en": "",
      "category": "🌸和食",
      "category1": "🌸和食",
      "detail_category": "🍣寿司",
      "category2": "🍣寿司",
      "city": "Düsseldorf",
      "region": "Düsseldorf",
      "area": "",
      "address": "Münsterstraße 510, 40472, Düsseldorf",
      "street": "Münsterstraße 510",
      "postcode": "40472",
      "country_code": "DE",
      "short_description": "",
      "description": "",
      "detail_comment": "",
      "description_en": "",
      "tags": "",
      "price": "€10–20",
      "rating": 0,
      "reviews_count": 30,
      "official_url": "http://www.sushitakushi.de/",
      "website": "http://www.sushitakushi.de/",
      "map_url": "https://www.google.com/maps/search/?api=1&query=Sushi%20Takushi&query_place_id=ChIJCcNQegDJuEcRnYUjzvePZ2g",
      "source_url": "",
      "phone": "",
      "opening_hours": "",
      "language_support": "",
      "latitude": null,
      "longitude": null,
      "last_reviewed_at": "2026-03-27T23:00:00.000Z",
      "updated_at": "2026-03-27T23:00:00.000Z"
    },
    {
      "id": "sushi-bar-maritim-platz",
      "slug": "sushi-bar-maritim-platz",
      "status": "active",
      "name": "Sushi-Bar SushiSho",
      "title": "Sushi-Bar SushiSho",
      "name_ja": "",
      "name_en": "",
      "category": "🌸和食",
      "category1": "🌸和食",
      "detail_category": "🍣寿司",
      "category2": "🍣寿司",
      "city": "Düsseldorf",
      "region": "Düsseldorf",
      "area": "",
      "address": "Maritim-Platz 1, 40474, Düsseldorf",
      "street": "Maritim-Platz 1",
      "postcode": "40474",
      "country_code": "DE",
      "short_description": "",
      "description": "",
      "detail_comment": "",
      "description_en": "",
      "tags": "",
      "price": "€30–40",
      "rating": 0,
      "reviews_count": 39,
      "official_url": "https://www.maritim.de/de/hotels/deutschland/hotel-duesseldorf/restaurants?utm_campaign=yext&utm_source=dussushisho&utm_medium=local",
      "website": "https://www.maritim.de/de/hotels/deutschland/hotel-duesseldorf/restaurants?utm_campaign=yext&utm_source=dussushisho&utm_medium=local",
      "map_url": "https://www.google.com/maps/search/?api=1&query=Sushi-Bar%20SushiSho&query_place_id=ChIJVQNzmNTJuEcRgO40wgfdsR8",
      "source_url": "",
      "phone": "",
      "opening_hours": "",
      "language_support": "",
      "latitude": null,
      "longitude": null,
      "last_reviewed_at": "2026-03-27T23:00:00.000Z",
      "updated_at": "2026-03-27T23:00:00.000Z"
    },
    {
      "id": "tachibana-ackerstrasse",
      "slug": "tachibana-ackerstrasse",
      "status": "active",
      "name": "Tachibana - Let It Roll",
      "title": "Tachibana - Let It Roll",
      "name_ja": "",
      "name_en": "",
      "category": "🌸和食",
      "category1": "🌸和食",
      "detail_category": "🍣寿司",
      "category2": "🍣寿司",
      "city": "Düsseldorf",
      "region": "Düsseldorf",
      "area": "",
      "address": "Ackerstraße 20, 40233, Düsseldorf",
      "street": "Ackerstraße 20",
      "postcode": "40233",
      "country_code": "DE",
      "short_description": "",
      "description": "",
      "detail_comment": "",
      "description_en": "",
      "tags": "",
      "price": "",
      "rating": 0,
      "reviews_count": 117,
      "official_url": "https://www.tachibanasushi.de/",
      "website": "https://www.tachibanasushi.de/",
      "map_url": "https://www.google.com/maps/search/?api=1&query=Tachibana%20-%20Let%20It%20Roll&query_place_id=ChIJXUGM1N7LuEcRjiiQ1shGIy4",
      "source_url": "",
      "phone": "",
      "opening_hours": "",
      "language_support": "",
      "latitude": null,
      "longitude": null,
      "last_reviewed_at": "2026-03-27T23:00:00.000Z",
      "updated_at": "2026-03-27T23:00:00.000Z"
    },
    {
      "id": "ChIJnximFjDKuEcRtbOeDNCb9Qw",
      "slug": "takezo-immermannstrasse",
      "status": "active",
      "name": "Takezo",
      "title": "Takezo",
      "name_ja": "",
      "name_en": "",
      "category": "🌸和食",
      "category1": "🌸和食",
      "detail_category": "🍜ラーメン",
      "category2": "🍜ラーメン",
      "city": "Düsseldorf",
      "region": "Düsseldorf",
      "area": "",
      "address": "Immermannstraße 48, 40210, Düsseldorf",
      "street": "Immermannstraße 48",
      "postcode": "40210",
      "country_code": "DE",
      "short_description": "",
      "description": "",
      "detail_comment": "",
      "description_en": "",
      "tags": "",
      "price": "€10–20",
      "rating": 0,
      "reviews_count": 7012,
      "official_url": "https://takezo.de/",
      "website": "https://takezo.de/",
      "map_url": "https://www.google.com/maps/search/?api=1&query=Takezo&query_place_id=ChIJnximFjDKuEcRtbOeDNCb9Qw",
      "source_url": "",
      "phone": "",
      "opening_hours": "",
      "language_support": "",
      "latitude": 51.2226986,
      "longitude": 6.7907142,
      "last_reviewed_at": "2026-03-27T23:00:00.000Z",
      "updated_at": "2026-03-27T23:00:00.000Z"
    },
    {
      "id": "ChIJVbR_sjrKuEcR6ji9wYBHTiA",
      "slug": "takumi-immermannstrasse",
      "status": "active",
      "name": "Takumi",
      "title": "Takumi",
      "name_ja": "",
      "name_en": "",
      "category": "🌸和食",
      "category1": "🌸和食",
      "detail_category": "🍜ラーメン",
      "category2": "🍜ラーメン",
      "city": "Düsseldorf",
      "region": "Düsseldorf",
      "area": "",
      "address": "Immermannstraße 28, 40210, Düsseldorf",
      "street": "Immermannstraße 28",
      "postcode": "40210",
      "country_code": "DE",
      "short_description": "",
      "description": "",
      "detail_comment": "",
      "description_en": "",
      "tags": "",
      "price": "€10–20",
      "rating": 0,
      "reviews_count": 8324,
      "official_url": "https://www.brickny.com/deutsch/unsere-restaurants/takumi-1st-de/",
      "website": "https://www.brickny.com/deutsch/unsere-restaurants/takumi-1st-de/",
      "map_url": "https://www.google.com/maps/search/?api=1&query=Takumi&query_place_id=ChIJVbR_sjrKuEcR6ji9wYBHTiA",
      "source_url": "",
      "phone": "",
      "opening_hours": "",
      "language_support": "",
      "latitude": 51.2236177,
      "longitude": 6.788777,
      "last_reviewed_at": "2026-03-27T23:00:00.000Z",
      "updated_at": "2026-03-27T23:00:00.000Z"
    },
    {
      "id": "ChIJyQs1FCXKuEcRLTCP74Mz6iU",
      "slug": "takumi-oststrasse",
      "status": "active",
      "name": "Takumi 2nd Tonkotsu",
      "title": "Takumi 2nd Tonkotsu",
      "name_ja": "",
      "name_en": "",
      "category": "🌸和食",
      "category1": "🌸和食",
      "detail_category": "🍜ラーメン",
      "category2": "🍜ラーメン",
      "city": "Düsseldorf",
      "region": "Düsseldorf",
      "area": "",
      "address": "Oststraße 51, 40211, Düsseldorf",
      "street": "Oststraße 51",
      "postcode": "40211",
      "country_code": "DE",
      "short_description": "",
      "description": "",
      "detail_comment": "",
      "description_en": "",
      "tags": "",
      "price": "€10–20",
      "rating": 0,
      "reviews_count": 2710,
      "official_url": "https://www.brickny.com/deutsch/unsere-restaurants/takumi-2nd-tonkotsu-de/",
      "website": "https://www.brickny.com/deutsch/unsere-restaurants/takumi-2nd-tonkotsu-de/",
      "map_url": "https://www.google.com/maps/search/?api=1&query=Takumi%202nd%20Tonkotsu&query_place_id=ChIJyQs1FCXKuEcRLTCP74Mz6iU",
      "source_url": "",
      "phone": "",
      "opening_hours": "",
      "language_support": "",
      "latitude": 51.2251692,
      "longitude": 6.7882311,
      "last_reviewed_at": "2026-03-27T23:00:00.000Z",
      "updated_at": "2026-03-27T23:00:00.000Z"
    },
    {
      "id": "ChIJNb2cRCXKuEcRZChVrbz87ug",
      "slug": "takumi-klosterstrasse",
      "status": "active",
      "name": "Takumi 3rd Chicken & Veggie",
      "title": "Takumi 3rd Chicken & Veggie",
      "name_ja": "",
      "name_en": "",
      "category": "🌸和食",
      "category1": "🌸和食",
      "detail_category": "🍜ラーメン",
      "category2": "🍜ラーメン",
      "city": "Düsseldorf",
      "region": "Düsseldorf",
      "area": "",
      "address": "Klosterstraße 72, 40211, Düsseldorf",
      "street": "Klosterstraße 72",
      "postcode": "40211",
      "country_code": "DE",
      "short_description": "",
      "description": "",
      "detail_comment": "",
      "description_en": "",
      "tags": "",
      "price": "€10–20",
      "rating": 0,
      "reviews_count": 1727,
      "official_url": "https://www.brickny.com/deutsch/unsere-restaurants/takumi-3rd-chicken-und-veggie-de/",
      "website": "https://www.brickny.com/deutsch/unsere-restaurants/takumi-3rd-chicken-und-veggie-de/",
      "map_url": "https://www.google.com/maps/search/?api=1&query=Takumi%203rd%20Chicken%20%26%20Veggie&query_place_id=ChIJNb2cRCXKuEcRZChVrbz87ug",
      "source_url": "",
      "phone": "",
      "opening_hours": "",
      "language_support": "",
      "latitude": 51.2247166,
      "longitude": 6.7889542,
      "last_reviewed_at": "2026-03-27T23:00:00.000Z",
      "updated_at": "2026-03-27T23:00:00.000Z"
    },
    {
      "id": "takumi-lorettostrasse",
      "slug": "takumi-lorettostrasse",
      "status": "active",
      "name": "Takumi 4th Loretto",
      "title": "Takumi 4th Loretto",
      "name_ja": "",
      "name_en": "",
      "category": "🌸和食",
      "category1": "🌸和食",
      "detail_category": "🍜ラーメン",
      "category2": "🍜ラーメン",
      "city": "Düsseldorf",
      "region": "Düsseldorf",
      "area": "",
      "address": "Lorettostraße 2, 40219, Düsseldorf",
      "street": "Lorettostraße 2",
      "postcode": "40219",
      "country_code": "DE",
      "short_description": "",
      "description": "",
      "detail_comment": "",
      "description_en": "",
      "tags": "",
      "price": "€10–20",
      "rating": 0,
      "reviews_count": 434,
      "official_url": "https://www.brickny.com/deutsch/unsere-restaurants/takumi-4th-loretto-de/",
      "website": "https://www.brickny.com/deutsch/unsere-restaurants/takumi-4th-loretto-de/",
      "map_url": "https://www.google.com/maps/search/?api=1&query=Takumi%204th%20Loretto&query_place_id=ChIJezZNl0rLuEcR4NVDFqRTohI",
      "source_url": "",
      "phone": "",
      "opening_hours": "",
      "language_support": "",
      "latitude": null,
      "longitude": null,
      "last_reviewed_at": "2026-03-27T23:00:00.000Z",
      "updated_at": "2026-03-27T23:00:00.000Z"
    },
    {
      "id": "ChIJXXQ5S9DLuEcRfI717NYKbrg",
      "slug": "takumi-immermannstrasse",
      "status": "active",
      "name": "Takumi 6th Spicy Tan Tan Men",
      "title": "Takumi 6th Spicy Tan Tan Men",
      "name_ja": "",
      "name_en": "",
      "category": "🌸和食",
      "category1": "🌸和食",
      "detail_category": "🍜ラーメン",
      "category2": "🍜ラーメン",
      "city": "Düsseldorf",
      "region": "Düsseldorf",
      "area": "",
      "address": "Immermannstraße 32, 40210, Düsseldorf",
      "street": "Immermannstraße 32",
      "postcode": "40210",
      "country_code": "DE",
      "short_description": "",
      "description": "",
      "detail_comment": "",
      "description_en": "",
      "tags": "",
      "price": "€10–20",
      "rating": 0,
      "reviews_count": 1336,
      "official_url": "https://www.brickny.com/deutsch/unsere-restaurants/takumi-6th-tantan-de/",
      "website": "https://www.brickny.com/deutsch/unsere-restaurants/takumi-6th-tantan-de/",
      "map_url": "https://www.google.com/maps/search/?api=1&query=Takumi%206th%20Spicy%20Tan%20Tan%20Men&query_place_id=ChIJXXQ5S9DLuEcRfI717NYKbrg",
      "source_url": "",
      "phone": "",
      "opening_hours": "",
      "language_support": "",
      "latitude": 51.2234451,
      "longitude": 6.7892636,
      "last_reviewed_at": "2026-03-27T23:00:00.000Z",
      "updated_at": "2026-03-27T23:00:00.000Z"
    },
    {
      "id": "ChIJhzsoLiXKuEcR2Q7zuqWX-7A",
      "slug": "tokyo-immermannstrasse",
      "status": "active",
      "name": "Tokyo Ramen Takeichi",
      "title": "Tokyo Ramen Takeichi",
      "name_ja": "",
      "name_en": "",
      "category": "🌸和食",
      "category1": "🌸和食",
      "detail_category": "🍜ラーメン",
      "category2": "🍜ラーメン",
      "city": "Düsseldorf",
      "region": "Düsseldorf",
      "area": "",
      "address": "Immermannstraße 18, 40210, Düsseldorf",
      "street": "Immermannstraße 18",
      "postcode": "40210",
      "country_code": "DE",
      "short_description": "",
      "description": "",
      "detail_comment": "",
      "description_en": "",
      "tags": "",
      "price": "€10–20",
      "rating": 0,
      "reviews_count": 3138,
      "official_url": "https://takeichi-ramen.eu/de/locations/germany/immermannstrasse-18-dusseldorf",
      "website": "https://takeichi-ramen.eu/de/locations/germany/immermannstrasse-18-dusseldorf",
      "map_url": "https://www.google.com/maps/search/?api=1&query=Tokyo%20Ramen%20Takeichi&query_place_id=ChIJhzsoLiXKuEcR2Q7zuqWX-7A",
      "source_url": "",
      "phone": "",
      "opening_hours": "",
      "language_support": "",
      "latitude": 51.224312,
      "longitude": 6.7873276,
      "last_reviewed_at": "2026-03-27T23:00:00.000Z",
      "updated_at": "2026-03-27T23:00:00.000Z"
    },
    {
      "id": "ChIJbaQxGcHLuEcRBexBA-hZzYY",
      "slug": "tokyo-bismarckstrasse",
      "status": "active",
      "name": "Tokyo Ramen Takeichi Bismarck",
      "title": "Tokyo Ramen Takeichi Bismarck",
      "name_ja": "",
      "name_en": "",
      "category": "🌸和食",
      "category1": "🌸和食",
      "detail_category": "🍜ラーメン",
      "category2": "🍜ラーメン",
      "city": "Düsseldorf",
      "region": "Düsseldorf",
      "area": "",
      "address": "Bismarckstraße 67, 40210, Düsseldorf",
      "street": "Bismarckstraße 67",
      "postcode": "40210",
      "country_code": "DE",
      "short_description": "",
      "description": "",
      "detail_comment": "",
      "description_en": "",
      "tags": "",
      "price": "€10–20",
      "rating": 0,
      "reviews_count": 942,
      "official_url": "https://takeichi-ramen.eu/",
      "website": "https://takeichi-ramen.eu/",
      "map_url": "https://www.google.com/maps/search/?api=1&query=Tokyo%20Ramen%20Takeichi%20Bismarck&query_place_id=ChIJbaQxGcHLuEcRBexBA-hZzYY",
      "source_url": "",
      "phone": "",
      "opening_hours": "",
      "language_support": "",
      "latitude": 51.2214349,
      "longitude": 6.7873113,
      "last_reviewed_at": "2026-03-27T23:00:00.000Z",
      "updated_at": "2026-03-27T23:00:00.000Z"
    },
    {
      "id": "ChIJ39utPjTLuEcROVKFIygUPLQ",
      "slug": "tsukiji-bahnstrasse",
      "status": "active",
      "name": "Tsukiji Sushi Seafood & more",
      "title": "Tsukiji Sushi Seafood & more",
      "name_ja": "",
      "name_en": "",
      "category": "🌸和食",
      "category1": "🌸和食",
      "detail_category": "🍣寿司",
      "category2": "🍣寿司",
      "city": "Düsseldorf",
      "region": "Düsseldorf",
      "area": "",
      "address": "Bahnstraße 63, 40210, Düsseldorf",
      "street": "Bahnstraße 63",
      "postcode": "40210",
      "country_code": "DE",
      "short_description": "",
      "description": "",
      "detail_comment": "",
      "description_en": "",
      "tags": "",
      "price": "€20–30",
      "rating": 0,
      "reviews_count": 278,
      "official_url": "http://www.tsukijidusseldorf.de/",
      "website": "http://www.tsukijidusseldorf.de/",
      "map_url": "https://www.google.com/maps/search/?api=1&query=Tsukiji%20Sushi%20Seafood%20%26%20more&query_place_id=ChIJ39utPjTLuEcROVKFIygUPLQ",
      "source_url": "",
      "phone": "",
      "opening_hours": "",
      "language_support": "",
      "latitude": 51.2194053,
      "longitude": 6.7849144,
      "last_reviewed_at": "2026-03-27T23:00:00.000Z",
      "updated_at": "2026-03-27T23:00:00.000Z"
    },
    {
      "id": "wukong-konrad-adenauer-platz",
      "slug": "wukong-konrad-adenauer-platz",
      "status": "active",
      "name": "Wukong Express Düsseldorf - Sushi & Nudel",
      "title": "Wukong Express Düsseldorf - Sushi & Nudel",
      "name_ja": "",
      "name_en": "",
      "category": "🌸和食",
      "category1": "🌸和食",
      "detail_category": "🍣寿司",
      "category2": "🍣寿司",
      "city": "Düsseldorf",
      "region": "Düsseldorf",
      "area": "",
      "address": "Konrad-Adenauer-Platz 9, 40210, Düsseldorf",
      "street": "Konrad-Adenauer-Platz 9",
      "postcode": "40210",
      "country_code": "DE",
      "short_description": "",
      "description": "",
      "detail_comment": "",
      "description_en": "",
      "tags": "",
      "price": "€1–10",
      "rating": 0,
      "reviews_count": 142,
      "official_url": "https://wukongexpress.com/",
      "website": "https://wukongexpress.com/",
      "map_url": "https://www.google.com/maps/search/?api=1&query=Wukong%20Express%20D%C3%BCsseldorf%20-%20Sushi%20%26%20Nudel&query_place_id=ChIJMaVrWv_LuEcRZ5nthDcVDRY",
      "source_url": "",
      "phone": "",
      "opening_hours": "",
      "language_support": "",
      "latitude": null,
      "longitude": null,
      "last_reviewed_at": "2026-03-27T23:00:00.000Z",
      "updated_at": "2026-03-27T23:00:00.000Z"
    },
    {
      "id": "ChIJb4b-QyXKuEcRdT9qJqtgobQ",
      "slug": "yabase-klosterstrasse",
      "status": "active",
      "name": "Yabase",
      "title": "Yabase",
      "name_ja": "",
      "name_en": "",
      "category": "🌸和食",
      "category1": "🌸和食",
      "detail_category": "🍣寿司",
      "category2": "🍣寿司",
      "city": "Düsseldorf",
      "region": "Düsseldorf",
      "area": "",
      "address": "Klosterstraße 70, 40211, Düsseldorf",
      "street": "Klosterstraße 70",
      "postcode": "40211",
      "country_code": "DE",
      "short_description": "",
      "description": "",
      "detail_comment": "",
      "description_en": "",
      "tags": "",
      "price": "$$$",
      "rating": 0,
      "reviews_count": 1954,
      "official_url": "http://yabase-ddf.com/",
      "website": "http://yabase-ddf.com/",
      "map_url": "https://www.google.com/maps/search/?api=1&query=Yabase&query_place_id=ChIJb4b-QyXKuEcRdT9qJqtgobQ",
      "source_url": "",
      "phone": "",
      "opening_hours": "",
      "language_support": "",
      "latitude": 51.2247963,
      "longitude": 6.7887578,
      "last_reviewed_at": "2026-03-27T23:00:00.000Z",
      "updated_at": "2026-03-27T23:00:00.000Z"
    },
    {
      "id": "ChIJcbETUADLuEcRYszEbo_ClGg",
      "slug": "yakitori-bismarckstrasse",
      "status": "active",
      "name": "Yakitori Numata",
      "title": "Yakitori Numata",
      "name_ja": "",
      "name_en": "",
      "category": "🌸和食",
      "category1": "🌸和食",
      "detail_category": "🍜ラーメン",
      "category2": "🍜ラーメン",
      "city": "Düsseldorf",
      "region": "Düsseldorf",
      "area": "",
      "address": "Bismarckstraße 96, 40210, Düsseldorf",
      "street": "Bismarckstraße 96",
      "postcode": "40210",
      "country_code": "DE",
      "short_description": "",
      "description": "",
      "detail_comment": "",
      "description_en": "",
      "tags": "",
      "price": "€20–30",
      "rating": 0,
      "reviews_count": 227,
      "official_url": "https://takeichi-ramen.eu/de/locations/germany/bismarckstrasse-96-dusseldorf",
      "website": "https://takeichi-ramen.eu/de/locations/germany/bismarckstrasse-96-dusseldorf",
      "map_url": "https://www.google.com/maps/search/?api=1&query=Yakitori%20Numata&query_place_id=ChIJcbETUADLuEcRYszEbo_ClGg",
      "source_url": "",
      "phone": "",
      "opening_hours": "",
      "language_support": "",
      "latitude": 51.2210225,
      "longitude": 6.7894951,
      "last_reviewed_at": "2026-03-27T23:00:00.000Z",
      "updated_at": "2026-03-27T23:00:00.000Z"
    },
    {
      "id": "yoko-kartäuserstrasse",
      "slug": "yoko-kartäuserstrasse",
      "status": "active",
      "name": "Yoko Sushi Lieferservice Düsseldorf Unterrath",
      "title": "Yoko Sushi Lieferservice Düsseldorf Unterrath",
      "name_ja": "",
      "name_en": "",
      "category": "🌸和食",
      "category1": "🌸和食",
      "detail_category": "🍣寿司",
      "category2": "🍣寿司",
      "city": "Düsseldorf",
      "region": "Düsseldorf",
      "area": "",
      "address": "Kartäuserstraße 1, 40468, Düsseldorf",
      "street": "Kartäuserstraße 1",
      "postcode": "40468",
      "country_code": "DE",
      "short_description": "",
      "description": "",
      "detail_comment": "",
      "description_en": "",
      "tags": "",
      "price": "€10–20",
      "rating": 0,
      "reviews_count": 126,
      "official_url": "https://www.yoko.de/",
      "website": "https://www.yoko.de/",
      "map_url": "https://www.google.com/maps/search/?api=1&query=Yoko%20Sushi%20Lieferservice%20D%C3%BCsseldorf%20Unterrath&query_place_id=ChIJk5vrWYTJuEcRSBFr3i_dhUY",
      "source_url": "",
      "phone": "",
      "opening_hours": "",
      "language_support": "",
      "latitude": null,
      "longitude": null,
      "last_reviewed_at": "2026-03-27T23:00:00.000Z",
      "updated_at": "2026-03-27T23:00:00.000Z"
    },
    {
      "id": "ChIJE-KsVuXLuEcR7SkaIwJEuIM",
      "slug": "zero-immermannstrasse",
      "status": "active",
      "name": "Zero Banchi",
      "title": "Zero Banchi",
      "name_ja": "",
      "name_en": "",
      "category": "🌸和食",
      "category1": "🌸和食",
      "detail_category": "🍣寿司",
      "category2": "🍣寿司",
      "city": "Düsseldorf",
      "region": "Düsseldorf",
      "area": "",
      "address": "Immermannstraße 34, 40210, Düsseldorf",
      "street": "Immermannstraße 34",
      "postcode": "40210",
      "country_code": "DE",
      "short_description": "",
      "description": "",
      "detail_comment": "",
      "description_en": "",
      "tags": "",
      "price": "€20–30",
      "rating": 0,
      "reviews_count": 771,
      "official_url": "https://www.brickny.com/deutsch/unsere-restaurants/zero-banchi-de/",
      "website": "https://www.brickny.com/deutsch/unsere-restaurants/zero-banchi-de/",
      "map_url": "https://www.google.com/maps/search/?api=1&query=Zero%20Banchi&query_place_id=ChIJE-KsVuXLuEcR7SkaIwJEuIM",
      "source_url": "",
      "phone": "",
      "opening_hours": "",
      "language_support": "",
      "latitude": 51.2233957,
      "longitude": 6.7894069,
      "last_reviewed_at": "2026-03-27T23:00:00.000Z",
      "updated_at": "2026-03-27T23:00:00.000Z"
    }
  ],
  "validation": {
    "source_count": 361,
    "explicitly_active_count": 361,
    "eligible_count": 63,
    "excluded_count": 298,
    "excluded_by_reason": {
      "status_not_active": 0,
      "placeholder_category": 298
    },
    "excluded_safe_ids": {
      "placeholder_category": [
        "ChIJ_XZ7TJ_LuEcR8KPuXFyN9q8",
        "ChIJ-wrI3TW3uEcRal5mMGg7US4",
        "ChIJ-zraXOzJuEcRg9vE1PQrI7Q",
        "ChIJ0-y56KrOuEcR4j2YNw9Do2A",
        "ChIJ055Eh3DLuEcRm1RGYxfa1pU",
        "ChIJ0x1bUVHJuEcRE7Z2EeuMufo",
        "ChIJ0yNuXsozv0cRg2av874kkTM",
        "ChIJ17fbzlrLuEcRwmaqjq3s24M",
        "ChIJ1aupx4PNuEcR1qPKkHOiJ4E",
        "ChIJ1UCgAenJuEcR55-kv_9c-0k",
        "ChIJ1UVeBGXJuEcRPUQp2RctFk8",
        "ChIJ1W5DOSXKuEcRzbNxS47R-Dc",
        "ChIJ1WDtQAbJuEcR5w3G-8bWFe8",
        "ChIJ20rMQL7LuEcREBCsHalOr80",
        "ChIJ302uoafJuEcRRTXo5s2mWuQ",
        "ChIJ33rNlmvKuEcRJwAZ8QCjeCI",
        "ChIJ37Ct-9vLuEcRhdUClDpwp4o",
        "ChIJ3w3rEiDLuEcRKn5grpPkUlk",
        "ChIJ3ybVG5_JuEcR03fUbcZjI5Y",
        "ChIJ3YQkdQjJuEcRZIXXElMg97Q",
        "ChIJ3ZQPTwDLuEcR7sci6XDAX-c",
        "ChIJ4-Z8wJjJuEcRfdXnfZDgnpU",
        "ChIJ4eMLbwDLuEcRjgQTAOgog34",
        "ChIJ4RsjuyG2uEcRWEIpHTMOVHw",
        "ChIJ4TbHNrXJuEcRiwnfvCQ4Ca0",
        "ChIJ4Y26OADLuEcRZUOsqvw6h_k",
        "ChIJ4zY0KrbLuEcRaD31LFG7NS8",
        "ChIJ5361Fm7JuEcRhFmsm7NhTR0",
        "ChIJ55ce-SjKuEcRs9ZdE3RiMgc",
        "ChIJ55OtO0rLuEcRB0JCMjSACUc",
        "ChIJ56L6_ArLuEcRD8Bm3YWtSfw",
        "ChIJ5ba79m3JuEcR_w6h3Dttxb0",
        "ChIJ61bzLLbLuEcRiBgGTe6mzys",
        "ChIJ6dlzR33JuEcRZDVyhrRlt6g",
        "ChIJ6USwYvHLuEcRCgVsk6iHjUM",
        "ChIJ6WjUOQDNuEcR2Kfz2Fay1C0",
        "ChIJ73T2KgXJuEcRlvfb6YLeh8Y",
        "ChIJ74YJG80yv0cRBKOSclE0aWU",
        "ChIJ76jSpp3JuEcRn8cV4Qy6DZk",
        "ChIJ79rWYAnJuEcRuUG0vu1-ji4",
        "ChIJ7aB93gm2uEcR7YoIqCzXnZI",
        "ChIJ7bkUv6LLuEcRf3Gec99xdwE",
        "ChIJ7c5DxZ3JuEcRQt5UJxXAzTM",
        "ChIJ7ejbEirLuEcRTP0_pM9cb04",
        "ChIJ7QRZfAXJuEcR_y2qrAmMlpg",
        "ChIJ7zEFPGbJuEcRA2vWMLgkwFA",
        "ChIJ8-v0g7zMuEcROceNZcpZ_x0",
        "ChIJ835WumXLuEcRMHBmeeau1ZA",
        "ChIJ999wgCTKuEcRjoNNqYaU9h4",
        "ChIJ99M1lr23uEcRqieR2rFh1IU"
      ]
    },
    "generated_count": 63,
    "map_eligible_count": 30,
    "intentionally_empty": false
  },
  "generated_at": "2026-07-13T21:48:07.234Z"
}
